m9s_stock_package_rate-7.0.3.dist-info/licenses/LICENSE
trytond/modules/stock_package_rate/__init__.py
trytond/modules/stock_package_rate/carrier.py
trytond/modules/stock_package_rate/carrier.xml
trytond/modules/stock_package_rate/message.xml
trytond/modules/stock_package_rate/mixin.py
trytond/modules/stock_package_rate/package.py
trytond/modules/stock_package_rate/sale.py
trytond/modules/stock_package_rate/sale.xml
trytond/modules/stock_package_rate/shipment.py
trytond/modules/stock_package_rate/shipment.xml
trytond/modules/stock_package_rate/tryton.cfg
trytond/modules/stock_package_rate/locale/de.po
trytond/modules/stock_package_rate/tests/__init__.py
trytond/modules/stock_package_rate/tests/test_module.py
trytond/modules/stock_package_rate/view/apply_shipping_select_rate_form.xml
trytond/modules/stock_package_rate/view/apply_shipping_start_form.xml
trytond/modules/stock_package_rate/view/carrier_form.xml
trytond/modules/stock_package_rate/view/sale_view_form.xml
trytond/modules/stock_package_rate/view/shipment_in_return_form.xml
trytond/modules/stock_package_rate/view/shipment_out_form.xml
m9s_stock_package_rate-7.0.3.dist-info/METADATA
m9s_stock_package_rate-7.0.3.dist-info/WHEEL
m9s_stock_package_rate-7.0.3.dist-info/entry_points.txt
m9s_stock_package_rate-7.0.3.dist-info/top_level.txt
m9s_stock_package_rate-7.0.3.dist-info/RECORD
